MANIFEST.in
README.rst
setup.py
l_pdseries_2_l_dfs/__init__.py
l_pdseries_2_l_dfs/func.py
l_pdseries_2_l_dfs.egg-info/PKG-INFO
l_pdseries_2_l_dfs.egg-info/SOURCES.txt
l_pdseries_2_l_dfs.egg-info/dependency_links.txt
l_pdseries_2_l_dfs.egg-info/not-zip-safe
l_pdseries_2_l_dfs.egg-info/top_level.txt