Metadata-Version: 1.2
Name: l-pdseries-2-l-dfs
Version: 0.1
Summary: Creating list of series to list of dfs
Home-page: http://github.com/YogenderPalChandra/pandasSeries2pandasDf
Author: Yogender Pal Chandra
Author-email: yogender027mae@gmail.com
License: MIT
Keywords: list of Pandas series to list of pandas data frame
Platform: UNKNOWN
Classifier: Development Status :: 3 - Alpha
Classifier: License :: OSI Approved :: MIT License
Classifier: Programming Language :: Python :: 3.7
Classifier: Topic :: Scientific/Engineering :: Visualization
Requires-Python: >=3.6
